AUTHORS
CHANGES
LICENSE
MANIFEST.in
README
TODO
setup.cfg
setup.py
Elixir.egg-info/PKG-INFO
Elixir.egg-info/SOURCES.txt
Elixir.egg-info/dependency_links.txt
Elixir.egg-info/requires.txt
Elixir.egg-info/top_level.txt
elixir/__init__.py
elixir/collection.py
elixir/entity.py
elixir/events.py
elixir/fields.py
elixir/options.py
elixir/properties.py
elixir/py23compat.py
elixir/relationships.py
elixir/statements.py
elixir/ext/__init__.py
elixir/ext/associable.py
elixir/ext/encrypted.py
elixir/ext/list.py
elixir/ext/perform_ddl.py
elixir/ext/versioned.py
examples/__init__.py
examples/videostore/dev.cfg
examples/videostore/devdata.sqlite
examples/videostore/setup.py
examples/videostore/start-videostore.py
examples/videostore/videostore/__init__.py
examples/videostore/videostore/json.py
examples/videostore/videostore/model.py
examples/videostore/videostore/release.py
examples/videostore/videostore.egg-info/PKG-INFO
examples/videostore/videostore.egg-info/SOURCES.txt
examples/videostore/videostore.egg-info/dependency_links.txt
examples/videostore/videostore.egg-info/not-zip-safe
examples/videostore/videostore.egg-info/paster_plugins.txt
examples/videostore/videostore.egg-info/requires.txt
examples/videostore/videostore.egg-info/sqlobject.txt
examples/videostore/videostore.egg-info/top_level.txt
examples/videostore/videostore/config/__init__.py
examples/videostore/videostore/config/app.cfg
examples/videostore/videostore/config/log.cfg
examples/videostore/videostore/controllers/__init__.py
examples/videostore/videostore/controllers/root.py
examples/videostore/videostore/static/css/login.css
examples/videostore/videostore/static/css/style.css
examples/videostore/videostore/static/images/favicon.ico
examples/videostore/videostore/static/images/info.png
examples/videostore/videostore/static/images/ok.png
examples/videostore/videostore/templates/__init__.py
examples/videostore/videostore/templates/actor.kid
examples/videostore/videostore/templates/director.kid
examples/videostore/videostore/templates/index.kid
examples/videostore/videostore/templates/login.kid
examples/videostore/videostore/templates/master.kid
examples/videostore/videostore/templates/movie.kid
examples/videostore/videostore/tests/__init__.py
examples/videostore/videostore/tests/test_controllers.py
examples/videostore/videostore/tests/test_model.py
tests/__init__.py
tests/a.py
tests/b.py
tests/test_acts_as_list.py
tests/test_associable.py
tests/test_autoload.py
tests/test_autosetup.py
tests/test_class_methods.py
tests/test_collections.py
tests/test_custombase.py
tests/test_dict.py
