Metadata-Version: 1.0
Name: Elixir
Version: 0.7.0
Summary: Declarative Mapper for SQLAlchemy
Home-page: http://elixir.ematia.de
Author: Gaetan de Menten, Daniel Haus and Jonathan LaCour
Author-email: sqlelixir@googlegroups.com
License: MIT License
Platform: UNKNOWN
Classifier: Development Status :: 5 - Production/Stable
Classifier: Intended Audience :: Developers
Classifier: License :: OSI Approved :: MIT License
Classifier: Operating System :: OS Independent
Classifier: Programming Language :: Python
Classifier: Topic :: Database :: Front-Ends
Classifier: Topic :: Software Development :: Libraries :: Python Modules
